normalize.py
normalize.css-2.3.4.data/scripts/normalize.py
normalize.css-2.3.4.dist-info/LICENSE
normalize.css-2.3.4.dist-info/METADATA
normalize.css-2.3.4.dist-info/WHEEL
normalize.css-2.3.4.dist-info/top_level.txt
normalize.css-2.3.4.dist-info/RECORD
