Metadata-Version: 2.1
Name: normalize.css
Version: 2.3.4
Summary: A modern, HTML5-ready alternative to CSS resets
Home-page: https://github.com/Ksengine/DicksonUI/extentions/normalize
Author: Kavindu Santhusa
Author-email: kavindusanthusa@gmail.com
License: MIT
Project-URL: Bug Tracker, https://github.com/Ksengine/DicksonUI/issues
Project-URL: Download, https://github.com/Ksengine/DicksonUI/releases
Platform: any
Classifier: Development Status :: 4 - Beta
Classifier: Operating System :: OS Independent
Classifier: Intended Audience :: Developers
Classifier: License :: OSI Approved :: MIT License
Classifier: Topic :: Internet :: WWW/HTTP :: Dynamic Content :: CGI Tools/Libraries
Classifier: Topic :: Internet :: WWW/HTTP :: HTTP Servers
Classifier: Topic :: Internet :: WWW/HTTP :: WSGI
Classifier: Topic :: Internet :: WWW/HTTP :: WSGI :: Application
Classifier: Topic :: Internet :: WWW/HTTP :: WSGI :: Middleware
Classifier: Topic :: Internet :: WWW/HTTP :: WSGI :: Server
Classifier: Topic :: Software Development :: Libraries :: Application Frameworks
Classifier: Programming Language :: Python :: 2.7
Classifier: Programming Language :: Python :: 3
Classifier: Programming Language :: Python :: 3.4
Classifier: Programming Language :: Python :: 3.5
Classifier: Programming Language :: Python :: 3.6
Classifier: Programming Language :: Python :: 3.7
